zensols/deepnlp/resources/bigbird.conf
zensols/deepnlp/resources/classify-batch.yml
zensols/deepnlp/resources/classify.conf
zensols/deepnlp/resources/cleaner.conf
zensols/deepnlp/resources/cli.conf
zensols/deepnlp/resources/crossval.conf
zensols/deepnlp/resources/default.conf
zensols/deepnlp/resources/embed-crf.conf
zensols/deepnlp/resources/fasttext.conf
zensols/deepnlp/resources/feature.conf
zensols/deepnlp/resources/glove.conf
zensols/deepnlp/resources/lang-batch.yml
zensols/deepnlp/resources/mask-fill.yml
zensols/deepnlp/resources/multilabel.yml
zensols/deepnlp/resources/obj.conf
zensols/deepnlp/resources/score.yml
zensols/deepnlp/resources/spacy-vectorizer.yml
zensols/deepnlp/resources/token-classify.yml
zensols/deepnlp/resources/transformer-expander.conf
zensols/deepnlp/resources/transformer-expander.yml
zensols/deepnlp/resources/transformer-sent.conf
zensols/deepnlp/resources/transformer.conf
zensols/deepnlp/resources/vectorizer.conf
zensols/deepnlp/resources/word2vec.conf
zensols/deepnlp/resources/wordembed.conf
zensols/deepnlp/resources/wordpiece.conf
zensols/deepnlp/__init__.py
zensols/deepnlp/cli.py
zensols/deepnlp/feature.py
zensols/deepnlp/score.py
zensols/deepnlp/classify/__init__.py
zensols/deepnlp/classify/domain.py
zensols/deepnlp/classify/facade.py
zensols/deepnlp/classify/model.py
zensols/deepnlp/classify/multilabel.py
zensols/deepnlp/classify/pred.py
zensols/deepnlp/embed/__init__.py
zensols/deepnlp/embed/doc.py
zensols/deepnlp/embed/domain.py
zensols/deepnlp/embed/fasttext.py
zensols/deepnlp/embed/glove.py
zensols/deepnlp/embed/word2vec.py
zensols/deepnlp/embed/wordtext.py
zensols/deepnlp/index/__init__.py
zensols/deepnlp/index/domain.py
zensols/deepnlp/index/lda.py
zensols/deepnlp/index/lsi.py
zensols/deepnlp/layer/__init__.py
zensols/deepnlp/layer/conv.py
zensols/deepnlp/layer/embed.py
zensols/deepnlp/layer/embrecurcrf.py
zensols/deepnlp/layer/wordvec.py
zensols/deepnlp/model/__init__.py
zensols/deepnlp/model/facade.py
zensols_deepnlp-1.19.0.dist-info/METADATA
zensols_deepnlp-1.19.0.dist-info/WHEEL
zensols_deepnlp-1.19.0.dist-info/licenses/LICENSE.md
zensols_deepnlp-1.19.0.dist-info/RECORD
