Metadata-Version: 2.3
Name: zensols_deepnlp
Version: 1.19.0
Summary: Deep learning utility library for natural language processing that aids in feature engineering and embedding layers.
Project-URL: Homepage, https://github.com/plandes/deepnlp
Project-URL: Documentation, https://plandes.github.io/deepnlp
Project-URL: Repository, https://github.com/plandes/deepnlp.git
Project-URL: Issues, https://github.com/plandes/deepnlp/issues
Project-URL: Changelog, https://github.com/plandes/deepnlp/blob/master/CHANGELOG.md
Author-email: Paul Landes <landes@mailc.net>
License: MIT
Keywords: deep learning,embedding,natural language processing,transformer
Requires-Python: <3.15,>=3.11
Requires-Dist: gensim~=4.4.0
Requires-Dist: h5py~=3.15.1
Requires-Dist: protobuf~=3.20.3
Requires-Dist: sentencepiece~=0.2.1
Requires-Dist: transformers~=4.54.1
Requires-Dist: zensols-deeplearn~=1.15.0
Requires-Dist: zensols-nlp~=1.13.1
